Kadal-0.2.1.dist-info/METADATA
Kadal-0.2.1.dist-info/RECORD
Kadal-0.2.1.dist-info/WHEEL
Kadal-0.2.1.dist-info/top_level.txt
kadal/__init__.py
kadal/client.py
kadal/media.py
kadal/old.py
kadal/query.py
kadal/request.py
kadal/user.py
kadal/utils.py
